ksei_mcp/__init__.py
ksei_mcp/main.py
ksei_mcp-1.4.0.dist-info/METADATA
ksei_mcp-1.4.0.dist-info/WHEEL
ksei_mcp-1.4.0.dist-info/entry_points.txt
ksei_mcp-1.4.0.dist-info/RECORD
