Metadata-Version: 2.4
Name: ksei-mcp
Version: 1.4.0
Summary: MCP server for KSEI API access
Project-URL: Homepage, https://github.com/nichsedge/ksei-mcp
Author: nichsedge
License: MIT
Requires-Python: >=3.11
Requires-Dist: aiohttp>=3.12.14
Requires-Dist: fake-useragent
Requires-Dist: mcp>=0.9.0
Requires-Dist: pyjwt
Requires-Dist: python-dotenv
Requires-Dist: requests
